serotools/__init__.py
serotools/cli.py
serotools/serotools.py
serotools-0.2.1.dist-info/AUTHORS.rst
serotools-0.2.1.dist-info/LICENSE
serotools-0.2.1.dist-info/METADATA
serotools-0.2.1.dist-info/WHEEL
serotools-0.2.1.dist-info/entry_points.txt
serotools-0.2.1.dist-info/top_level.txt
serotools-0.2.1.dist-info/RECORD
