Metadata-Version: 2.1
Name: serotools
Version: 0.2.1
Summary: This package serves as a toolkit and repository for the White-Kauffmann-Le Minor scheme for Salmonella serotyping, which defines nomenclature and antigenic factors for each recognized serovar. The scheme is made available in multiple formats, along with methods for querying and comparing serovar names and antigenic formulae, as well as determining the most abundant serovar for a cluster of isolates.
Home-page: https://github.com/CFSAN-Biostatistics/serotools
Author: Joseph D. Baugher, Ph.D.
Author-email: joseph.baugher@fda.hhs.gov
License: BSD
Keywords: bioinformatics,Salmonella,serovar,serotype,serotyping,White-Kauffmann-Le Minor
Platform: UNKNOWN
Classifier: Development Status :: 4 - Beta
Classifier: Intended Audience :: Developers
Classifier: Intended Audience :: Science/Research
Classifier: License :: OSI Approved :: BSD License
Classifier: Natural Language :: English
Classifier: Programming Language :: Python :: 3
Classifier: Programming Language :: Python :: 3.5
Classifier: Programming Language :: Python :: 3.6
Classifier: Programming Language :: Python :: 3.7
Classifier: Programming Language :: Python :: 3.8
Requires-Dist: numpy
Requires-Dist: pandas
